idstool/__init__.py
idstool/ids_classes.py
idstool/serializer.py
idstool-0.1.3.dist-info/LICENSE
idstool-0.1.3.dist-info/METADATA
idstool-0.1.3.dist-info/WHEEL
idstool-0.1.3.dist-info/top_level.txt
idstool-0.1.3.dist-info/RECORD
