Metadata-Version: 2.1
Name: idstool
Version: 0.1.3
Summary: Python Tool to create IDS (Information delivery specification) files
Author-email: Alexander Hammett <alexander.hammett@preisigag.ch>
Project-URL: Homepage, https://github.com/alexander-hammett/idstool
Keywords: IDS,Information Delivery Specification,openBIM
Classifier: Programming Language :: Python :: 3
Requires-Python: >=3.10
License-File: LICENSE
